{"relatedGroup":{"rxcui":"6813","termType":["SCD","SBD"],"conceptGroup":[{"tty":"SBD","conceptProperties":[{"rxcui":"864708","name":"Methadone Hydrochloride 10 MG Oral Tablet [Dolophine]","synonym":"Dolophine 10 MG Oral Tablet","tty":"SBD","language":"ENG","suppress":"N","umlscui":"C0708064"},{"rxcui":"864720","name":"Methadone Hydrochloride 5 MG Oral Tablet [Dolophine]","synonym":"Dolophine 5 MG Oral Tablet","tty":"SBD","language":"ENG","suppress":"N","umlscui":"C0708062"},{"rxcui":"864737","name":"Methadone Hydrochloride 5 MG Oral Tablet [Methadose]","synonym":"Methadose 5 MG Oral Tablet","tty":"SBD","language":"ENG","suppress":"N","umlscui":"C0708063"},{"rxcui":"864980","name":"Methadone Hydrochloride 0.333 MG/ML Oral Suspension [Methadose]","synonym":"Methadose 0.333 MG/ML Oral Suspension","tty":"SBD","language":"ENG","suppress":"N","umlscui":"C0708068"},{"rxcui":"991149","name":"Methadone Hydrochloride 10 MG/ML Oral Solution [Methadose]","synonym":"Methadose 10 MG per 1 ML Concentrate for Oral Solution","tty":"SBD","language":"ENG","suppress":"N","umlscui":"C0708051"}]},{"tty":"SCD","conceptProperties":[{"rxcui":"864706","name":"Methadone Hydrochloride 10 MG Oral Tablet","synonym":"","tty":"SCD","language":"ENG","suppress":"N","umlscui":"C0978492"},{"rxcui":"864714","name":"Methadone Hydrochloride 10 MG/ML Injectable Solution","synonym":"","tty":"SCD","language":"ENG","suppress":"N","umlscui":"C0708055"},{"rxcui":"864718","name":"Methadone Hydrochloride 5 MG Oral Tablet","synonym":"","tty":"SCD","language":"ENG","suppress":"N","umlscui":"C0981584"},{"rxcui":"864751","name":"Methadone Hydrochloride 0.4 MG/ML Oral Solution","synonym":"methadone hydrochloride 2 MG per 5 ML Syrup","tty":"SCD","language":"ENG","suppress":"N","umlscui":"C0358826"},{"rxcui":"864761","name":"Methadone Hydrochloride 1 MG/ML Oral Solution","synonym":"methadone hydrochloride 5 MG per 5 ML Oral Solution","tty":"SCD","language":"ENG","suppress":"N","umlscui":"C0978498"},{"rxcui":"864769","name":"Methadone Hydrochloride 2 MG/ML Oral Solution","synonym":"methadone hydrochloride 10 MG per 5 ML Oral Solution","tty":"SCD","language":"ENG","suppress":"N","umlscui":"C0978494"},{"rxcui":"864794","name":"Methadone Hydrochloride 25 MG/ML Injectable Solution","synonym":"","tty":"SCD","language":"ENG","suppress":"N","umlscui":"C1343230"},{"rxcui":"864828","name":"Methadone Hydrochloride 50 MG/ML Injectable Solution","synonym":"","tty":"SCD","language":"ENG","suppress":"N","umlscui":"C1342078"},{"rxcui":"864978","name":"Methadone Hydrochloride 0.333 MG/ML Oral Suspension","synonym":"methadone hydrochloride 40 MG Dispersible Tablet for Oral Suspension","tty":"SCD","language":"ENG","suppress":"N","umlscui":"C1134431"},{"rxcui":"864984","name":"Methadone Hydrochloride 20 MG/ML Oral Solution","synonym":"methadone hydrochloride 20 MG/ML Concentrate for Oral Solution","tty":"SCD","language":"ENG","suppress":"N","umlscui":"C0793276"},{"rxcui":"991147","name":"Methadone Hydrochloride 10 MG/ML Oral Solution","synonym":"methadone hydrochloride 10 MG per 1 ML Concentrate for Oral Solution","tty":"SCD","language":"ENG","suppress":"N","umlscui":"C0978495"}]}]}}